Metadata-Version: 2.1
Name: bugu-bot
Version: 1.1
Summary: 适用于nb的孤寡机器人插件
Home-page: https://github.com/Sclock/bugu_bot
Author: Sclock
Author-email: 1342810270@qq.com
License: UNKNOWN
Platform: UNKNOWN
